peewee_extra_fields/__init__.py
peewee_extra_fields/ar_fields.py
peewee_extra_fields/country-data.json
peewee_extra_fields/currency-data.json
peewee_extra_fields/exceptions.py
peewee_extra_fields/int2country.json
peewee_extra_fields/int2currency.json
peewee_extra_fields/languages-data.json
peewee_extra_fields/legacy_fields.py
peewee_extra_fields/regex_fields.py
peewee_extra_fields/us_fields.py
peewee_extra_fields-2.8.2.dist-info/LICENSE
peewee_extra_fields-2.8.2.dist-info/METADATA
peewee_extra_fields-2.8.2.dist-info/WHEEL
peewee_extra_fields-2.8.2.dist-info/top_level.txt
peewee_extra_fields-2.8.2.dist-info/zip-safe
peewee_extra_fields-2.8.2.dist-info/RECORD
