Metadata-Version: 2.1
Name: peewee-extra-fields
Version: 2.8.2
Summary: Extra fields for Peewee
Home-page: https://github.com/juancarlospaco/peewee-extra-fields
Author: Juan Carlos
Author-email: juancarlospaco@gmail.com
Maintainer: Juan Carlos
Maintainer-email: juancarlospaco@gmail.com
License: GPL-3 LGPL-3
Download-URL: https://github.com/juancarlospaco/peewee-extra-fields
Project-URL: Docs, https://github.com/juancarlospaco/peewee-extra-fields/README.md
Project-URL: Bugs, https://github.com/juancarlospaco/peewee-extra-fields/issues
Keywords: peewee,minimalism,orm,iso3166,iso4217,iso639,ipv4-address,ipv6-address,csv,orm-extension,python3,argentina
Platform: Linux
Platform: Darwin
Platform: Windows
Classifier: Development Status :: 5 - Production/Stable
Classifier: Development Status :: 6 - Mature
Classifier: Environment :: Console
Classifier: Environment :: X11 Applications
Classifier: Environment :: No Input/Output (Daemon)
Classifier: Environment :: Other Environment
Classifier: Intended Audience :: Developers
Classifier: Intended Audience :: System Administrators
Classifier: Intended Audience :: Other Audience
Classifier: Natural Language :: English
Classifier: License :: OSI Approved :: GNU General Public License (GPL)
Classifier: License :: OSI Approved :: GNU Library or Lesser General Public License (LGPL)
Classifier: License :: OSI Approved :: GNU Lesser General Public License v3 or later (LGPLv3+)
Classifier: License :: OSI Approved :: GNU General Public License v3 or later (GPLv3+)
Classifier: Operating System :: OS Independent
Classifier: Operating System :: POSIX :: Linux
Classifier: Operating System :: Microsoft :: Windows
Classifier: Operating System :: MacOS :: MacOS X
Classifier: Programming Language :: Python
Classifier: Programming Language :: Python :: 3
Classifier: Programming Language :: Python :: 3 :: Only
Classifier: Programming Language :: Python :: Implementation :: CPython
Classifier: Topic :: Software Development
Classifier: Topic :: Software Development :: Libraries
Classifier: Topic :: Software Development :: Libraries :: Python Modules
Provides: peewee_extra_fields
Requires-Python: >=3.8
Requires-Dist: peewee
Requires-Dist: psycopg2-binary
